README.md
setup.cfg
setup.py
distributions_rcm/Binomialdistribution.py
distributions_rcm/Gaussiandistribution.py
distributions_rcm/Generaldistribution.py
distributions_rcm/__init__.py
distributions_rcm.egg-info/PKG-INFO
distributions_rcm.egg-info/SOURCES.txt
distributions_rcm.egg-info/dependency_links.txt
distributions_rcm.egg-info/not-zip-safe
distributions_rcm.egg-info/top_level.txt